pinnstorch
tests
