Metadata-Version: 2.1
Name: pinnstorch
Version: 0.1.2
Summary: An implementation of PINNs in PyTorch using Lightning and Hydra.
Home-page: https://github.com/rezaakb/pinns-torch
Author: Reza Akbarian Bafghi
Author-email: reza.akbarianbafghi@coloardo.edu
License: BSD-3-Clause
Classifier: Development Status :: 2 - Pre-Alpha
Classifier: Programming Language :: Python :: 3.9
Classifier: Programming Language :: Python :: 3.10
License-File: LICENSE
